DataPreprocessor/__init__.py
DataPreprocessor/data_preprocessor.py
DatasetPreprocessor-0.1.1.dist-info/METADATA
DatasetPreprocessor-0.1.1.dist-info/WHEEL
DatasetPreprocessor-0.1.1.dist-info/top_level.txt
DatasetPreprocessor-0.1.1.dist-info/RECORD
